{
    "description": "项目配置文件",
    "packOptions": {
        "ignore": [
            {
                "value": "demo",
                "type": "folder"
            }
        ],
        "include": []
    },
    "setting": {
        "urlCheck": false,
        "es6": true,
        "postcss": true,
        "minified": true,
        "newFeature": true,
        "coverView": true,
        "nodeModules": true,
        "autoAudits": false,
        "uglifyFileName": true,
        "checkInvalidKey": true,
        "checkSiteMap": true,
        "uploadWithSourceMap": true,
        "babelSetting": {
            "ignore": [],
            "disablePlugins": [],
            "outputPath": ""
        }
    },
    "compileType": "miniprogram",
    "libVersion": "2.29.0",
    "appid": "wxf5c12af7ff8334c4",
    "projectname": "atree",
    "simulatorType": "wechat",
    "simulatorPluginLibVersion": {},
    "condition": {},
    "editorSetting": {
        "tabIndent": "insertSpaces",
        "tabSize": 4
    }
}